pyweierstrass/__init__.py
pyweierstrass/weierstrass.py
pyweierstrass-0.2.3.dist-info/LICENSE
pyweierstrass-0.2.3.dist-info/WHEEL
pyweierstrass-0.2.3.dist-info/METADATA
pyweierstrass-0.2.3.dist-info/RECORD
